pingboard/__init__.py
pingboard/const.py
pingboard/io.py
pingboard/ui.py
pingboard/util.py
pingboard-1.0.2.dist-info/LICENSE
pingboard-1.0.2.dist-info/METADATA
pingboard-1.0.2.dist-info/WHEEL
pingboard-1.0.2.dist-info/entry_points.txt
pingboard-1.0.2.dist-info/top_level.txt
pingboard-1.0.2.dist-info/RECORD
