Metadata-Version: 2.1
Name: pingboard
Version: 1.0.2
Summary: This curses based script displays a dashboard of hosts that it sends ICMP echo request packets (i.e. ping) and their responses
Home-page: http://bitbucket.org/go8ose/pingboard
Author: Geoff Crompton
Author-email: geoff+pingboard@cromp.id.au
License: GPL3+
Platform: UNKNOWN
Classifier: Development Status :: 5 - Production/Stable
Classifier: Environment :: Console :: Curses
Classifier: Intended Audience :: Information Technology
Classifier: License :: OSI Approved :: GNU General Public License v3 or later (GPLv3+)
Classifier: Natural Language :: English
Classifier: Operating System :: Unix
Classifier: Programming Language :: Python
Classifier: Topic :: Internet
Classifier: Topic :: System :: Networking :: Monitoring
Classifier: Topic :: System :: Systems Administration
Classifier: Topic :: Utilities
